README.md
setup.py
datacatalog/__init__.py
datacatalog/api_client.py
datacatalog/configuration.py
datacatalog/exceptions.py
datacatalog/rest.py
datacatalog/api/__init__.py
datacatalog/api/datasets_api.py
datacatalog/api/resources_api.py
datacatalog/api/standard_variables_api.py
datacatalog/api/variables_api.py
datacatalog/models/__init__.py
datacatalog/models/dataset.py
datacatalog/models/inline_object.py
datacatalog/models/inline_object1.py
datacatalog/models/inline_object10.py
datacatalog/models/inline_object11.py
datacatalog/models/inline_object12.py
datacatalog/models/inline_object2.py
datacatalog/models/inline_object3.py
datacatalog/models/inline_object4.py
datacatalog/models/inline_object5.py
datacatalog/models/inline_object6.py
datacatalog/models/inline_object7.py
datacatalog/models/inline_object8.py
datacatalog/models/inline_object9.py
datacatalog/models/inline_response200.py
datacatalog/models/inline_response2001.py
datacatalog/models/inline_response2001_dataset.py
datacatalog/models/inline_response2001_dataset_variables.py
datacatalog/models/inline_response2002.py
datacatalog/models/inline_response2002_dataset.py
datacatalog/models/inline_response2002_dataset_resources.py
datacatalog/models/inline_response2003.py
datacatalog/models/inline_response2003_dataset.py
datacatalog/models/inline_response2004.py
datacatalog/models/inline_response2004_dataset.py
datacatalog/models/inline_response2004_dataset_variables.py
datacatalog/models/inline_response2005.py
datacatalog/models/inline_response2005_dataset.py
datacatalog/models/inline_response2006.py
datacatalog/models/inline_response2006_dataset.py
datacatalog/models/inline_response2007.py
datacatalog/models/inline_response2007_dataset.py
datacatalog/models/inline_response200_dataset.py
datacatalog/models/inline_response200_dataset_standard_variables.py
datacatalog/models/provenance.py
datacatalog/models/resource.py
datacatalog/models/standard_variable.py
datacatalog/models/variable.py
datacatalog_api.egg-info/PKG-INFO
datacatalog_api.egg-info/SOURCES.txt
datacatalog_api.egg-info/dependency_links.txt
datacatalog_api.egg-info/requires.txt
datacatalog_api.egg-info/top_level.txt
test/test_dataset.py
